{
    "name": "eBlipColour",
    "module": "CRadar",
    "scope": "",
    "width": 4,
    "isClass": false,
    "isHexademical": false,
    "isSigned": false,
    "isBitfield": false,
    "comment": "",
    "members": [
        {
            "name": "BLIP_COLOUR_RED",
            "value": 0
        },
        {
            "name": "BLIP_COLOUR_GREEN",
            "value": 1
        },
        {
            "name": "BLIP_COLOUR_LIGHT_BLUE",
            "value": 2
        },
        {
            "name": "BLIP_COLOUR_GRAY",
            "value": 3
        },
        {
            "name": "BLIP_COLOUR_YELLOW",
            "value": 4
        },
        {
            "name": "BLIP_COLOUR_MAGENTA",
            "value": 5
        },
        {
            "name": "BLIP_COLOUR_CYAN",
            "value": 6
        }
    ]
}